{
  "songs": [
    {
      "id": 0,
      "title": "Back to Friends",
      "lyrics": [
        {"time": 0, "text": "Touch my body tender"},
        {"time": 5, "text": "'Cause the feeling makes me weak"},
        {"time": 10, "text": "Kicking off the covers"},
        {"time": 15, "text": "I see the ceiling, while you're looking down at me"},
        {"time": 15, "text": "How can we go back to being friends"},
        {"time": 15, "text": "When we just shared a bed?"},
        {"time": 15, "text": "How can you look at me and pretend"},
        {"time": 15, "text": "I'm someone you've never met?"},
        {"time": 15, "text": "It was last December?"},
        {"time": 15, "text": "You were layin' on my chest?"},
        {"time": 15, "text": "I still remember?"},
        {"time": 15, "text": "I was scared to take a breath, didn't want you to move your head?"},
        {"time": 15, "text": "How can we go back to being friends"},
        {"time": 15, "text": "When we just shared a bed? (Yeah)"},
        {"time": 15, "text": "How can you look at me and pretend"},
        {"time": 15, "text": "I'm someone you've never met?"},
        {"time": 15, "text": "The devil in your eyes"},
        {"time": 15, "text": "Won't deny the lies"},
        {"time": 15, "text": "You've sold, I'm holding on too tight"},
        {"time": 15, "text": "While you let go, this is casual"},
        {"time": 15, "text": "How can we go back to being friends"},
        {"time": 15, "text": "When we just shared a bed? (Yeah)"},
        {"time": 15, "text": "How can you look at me and pretend"},
        {"time": 15, "text": "I'm someone you've never met?"},
        {"time": 15, "text": "How can we go back to being friends"},
        {"time": 15, "text": "When we just shared a bed? (Yeah)"},
        {"time": 15, "text": "How can you look at me and pretend"},
        {"time": 15, "text": "I'm someone you've never met?"},
        {"time": 15, "text": "I'm someone you've never met"},
        {"time": 15, "text": "Oh yeah"}
      ]
    },
    {
      "id": 1,
      "title": "Terlalu Tinggi",
      "lyrics": [
        {"time": 0, "text": "Ikatkan padaku"},
        {"time": 5, "text": "Tali benang terpanjang"},
        {"time": 10, "text": "Agar 'ku bisa kau terbangkan"},
        {"time": 15, "text": "Sejauh yang kamu mau"},
        {"time": 15, "text": "Angin kencang"},
        {"time": 15, "text": "Bawakan kesenangan"},
        {"time": 15, "text": "Dapat buatmu terbangkanku"},
        {"time": 15, "text": "Sejauh yang kamu mau"},
        {"time": 15, "text": "Dengan senang kau terbangkan aku"},
        {"time": 15, "text": "Terlalu tinggi"},
        {"time": 15, "text": "Terlalu tinggi"},
        {"time": 15, "text": "Di atas awan kunikmati dua sisi"},
        {"time": 15, "text": "Indah tebang terlalu tinggi"},
        {"time": 15, "text": "Takut jatuh, terlalu jauh"},
        {"time": 15, "text": "Semakin tinggi"},
        {"time": 15, "text": "Semakin jauh 'ku melihat"},
        {"time": 15, "text": "Apakah engkau gengam erat"},
        {"time": 15, "text": "Tarik aku lebih dekat"},
        {"time": 15, "text": "Kumohon jangan kau lepaskanku"},
        {"time": 15, "text": "Angin kencang"},
        {"time": 15, "text": "Bawakan kesenangan"},
        {"time": 15, "text": "Dapat buatmu terbangkanku"},
        {"time": 15, "text": "Sejauh yang kamu mau"},
        {"time": 15, "text": "Dengan senang kau terbangkan aku"},
        {"time": 15, "text": "Terlalu tinggi"},
        {"time": 15, "text": "Terlalu tinggi"},
        {"time": 15, "text": "Di atas awan kunikmati dua sisi"},
        {"time": 15, "text": "Indah tebang terlalu tinggi"},
        {"time": 15, "text": "Takut jatuh, terlalu jauh"},
        {"time": 15, "text": "Semakin tinggi"},
        {"time": 15, "text": "Semakin jauh 'ku melihat"},
        {"time": 15, "text": "Apakah engkau gengam erat"},
        {"time": 15, "text": "Tarik aku lebih dekat"},
        {"time": 15, "text": "Kumohon jangan kau lepaskanku"},
        {"time": 15, "text": "Di atas awan kunikmati dua sisi"},
        {"time": 15, "text": "Indah tebang terlalu tinggi"},
        {"time": 15, "text": "Takut jatuh, terlalu jauh"},
        {"time": 15, "text": "Semakin tinggi"},
        {"time": 15, "text": "Semakin jauh 'ku melihat"},
        {"time": 15, "text": "Apakah engkau gengam erat"},
        {"time": 15, "text": "Tarik aku lebih dekat"},
        {"time": 15, "text": "Kumohon jangan kau lepas"},
        {"time": 15, "text": "Kumohon jangan kau lepaskan aku"},
        {"time": 15, "text": "Lepaskan aku"}
      ]
    },
    {
      "id": 2,
      "title": "Versace On The Floor",
      "lyrics": [
        {"time": 0, "text": "Song begins..."},
        {"time": 5, "text": "Let's take our time tonight"},
        {"time": 10, "text": "Above us all the stars are watching"},
        {"time": 15, "text": "There's no place I'd rather be"},
        {"time": 15, "text": "Your eyes are where I'm lost in"},
        {"time": 15, "text": "Underneath the chandelier"},
        {"time": 15, "text": "We're dancin' all alone"},
        {"time": 15, "text": "There's no reason to hide"},
        {"time": 15, "text": "What we're feelin' inside right now"},
        {"time": 15, "text": "So, baby, let's just turn down the lights and close the door"},
        {"time": 15, "text": "Ooh, I love that dress, but you won't need it anymore"},
        {"time": 15, "text": "No, you won't need it no more"},
        {"time": 15, "text": "Let's just kiss 'til we're naked, baby"},
        {"time": 15, "text": "Versace on the floor"},
        {"time": 15, "text": "Ooh, take it off for me, for me, for me, for me now, girl"},
        {"time": 15, "text": "Versace on the floor"},
        {"time": 15, "text": "Ooh, take it off for me, for me, for me, for me now, girl, mm"},
        {"time": 15, "text": "I'll unzip the back and watch it fall"},
        {"time": 15, "text": "While I kiss your neck and shoulders"},
        {"time": 15, "text": "No, don't be afraid to show it all"},
        {"time": 15, "text": "I'll be right here, ready to hold ya"},
        {"time": 15, "text": "Girl, you know you're perfect from"},
        {"time": 15, "text": "Your head down to your heels"},
        {"time": 15, "text": "Don't be confused by my smile"},
        {"time": 15, "text": "'Cause I ain't never been more for real, for real"},
        {"time": 15, "text": "So just turn down the lights (down the lights) and close the door (close the door)"},
        {"time": 15, "text": "Ooh, I love that dress, but you won't need it anymore"},
        {"time": 15, "text": "No, you won't need it no more"},
        {"time": 15, "text": "Let's just kiss 'til we're naked, baby"},
        {"time": 15, "text": "Versace on the floor"},
        {"time": 15, "text": "Ooh, take it off for me, for me, for me, for me now, girl"},
        {"time": 15, "text": "Versace on the floor"},
        {"time": 15, "text": "Ooh, take it off for me, for me, for me, for me now, girl"},
        {"time": 15, "text": "Dance"},
        {"time": 15, "text": "(It's warmin' up) can you feel it?"},
        {"time": 15, "text": "(It's warmin' up) can you feel it?"},
        {"time": 15, "text": "(It's warmin' up) can you feel it, baby?"},
        {"time": 15, "text": "(It's warmin' up) oh, seems like you're ready for more, more, more"},
        {"time": 15, "text": "Let's just kiss 'til we're naked"},
        {"time": 15, "text": "Ooh, Versace on the floor"},
        {"time": 15, "text": "Hey, baby, take it off for me, for me, for me, for me now, girl"},
        {"time": 15, "text": "Versace on the floor"},
        {"time": 15, "text": "Oh, oh, take it off for me, for me, for me, for me now, girl"},
        {"time": 15, "text": "Versace on the floor"},
        {"time": 15, "text": "Floor"},
        {"time": 15, "text": "Floor"}
      ]
    },
    {
      "id": 3,
      "title": "Ride",
      "lyrics": [
        {"time": 13, "text": "I just wanna stay"},
        {"time": 15, "text": "In the sun where I find"},
        {"time": 16, "text": "I know it's hard sometimes"},
        {"time": 18, "text": "Pieces of peace in the sun's peace of mind"},
        {"time": 20, "text": "I know it's hard sometimes"},
        {"time": 20, "text": "Yeah, I think about the end just way too much"},
        {"time": 20, "text": "But it's fun to fantasize"},
        {"time": 20, "text": "On my enemies, I wouldn't wish who I was"},
        {"time": 20, "text": "But it's fun to fantasize"},
        {"time": 20, "text": "Oh, oh, I'm fallin'"},
        {"time": 20, "text": "So I'm takin' my time on my ride"},
        {"time": 20, "text": "Oh, I'm fallin'"},
        {"time": 20, "text": "So I'm takin' my time on my ride"},
        {"time": 20, "text": "Takin' my time on my ride"},
        {"time": 20, "text": "\"I'd die for you,\" that's easy to say"},
        {"time": 20, "text": "We have a list of people that we would take"},
        {"time": 20, "text": "A bullet for them, a bullet for you"},
        {"time": 20, "text": "A bullet for everybody in this room"},
        {"time": 20, "text": "But I don't seem to see many bullets comin' through"},
        {"time": 20, "text": "See many bullets comin' through"},
        {"time": 20, "text": "Metaphorically, I'm the man"},
        {"time": 20, "text": "But literally, I don't know what I'd do"},
        {"time": 20, "text": "\"I'd live for you,\" and that's hard to do"},
        {"time": 20, "text": "Even harder to say when you know it's not true"},
        {"time": 20, "text": "Even harder to write when you know that tonight"},
        {"time": 20, "text": "There were people back home who tried talking to you"},
        {"time": 20, "text": "But then you ignore them still"},
        {"time": 20, "text": "All these questions, they're for real"},
        {"time": 20, "text": "Like, \"Who would you live for?\" \"Who would you die for?\""},
        {"time": 20, "text": "And \"Would you ever kill?\""},
        {"time": 20, "text": "Oh, oh, I'm fallin'"},
        {"time": 20, "text": "So I'm takin' my time on my ride"},
        {"time": 20, "text": "Oh, I'm fallin'"},
        {"time": 20, "text": "So I'm takin' my time on my ride"},
        {"time": 20, "text": "Takin' my time on my ride"},
        {"time": 20, "text": "I've been thinkin' too much"},
        {"time": 20, "text": "I've been thinkin' too much"},
        {"time": 20, "text": "I've been thinkin' too much"},
        {"time": 20, "text": "I've been thinkin' too much (help me)"},
        {"time": 20, "text": "I've been thinkin' too much (I've been thinkin' too much)"},
        {"time": 20, "text": "I've been thinkin' too much (help me)"},
        {"time": 20, "text": "I've been thinkin' too much (I've been thinkin' too much)"},
        {"time": 20, "text": "I've been thinkin' too much"},
        {"time": 20, "text": "Oh, oh, I'm fallin'"},
        {"time": 20, "text": "So I'm takin' my time on my ride"},
        {"time": 20, "text": "Oh, I'm fallin'"},
        {"time": 20, "text": "So I'm takin' my time"},
        {"time": 20, "text": "Takin' my time on my ride"},
        {"time": 20, "text": "Whoa (whoo, yeah)"},
        {"time": 20, "text": "Oh, oh, I'm fallin'"},
        {"time": 20, "text": "So I'm takin' my time on my ride"},
        {"time": 20, "text": "Oh, I'm fallin'"},
        {"time": 20, "text": "So I'm takin' my time on my-"},
        {"time": 20, "text": "I've been thinkin' too much, help me"},
        {"time": 20, "text": "I've been thinkin' too much, help me"},
        {"time": 20, "text": "I've been thinkin' too much (I've been thinkin' too much)"},
        {"time": 20, "text": "I've been thinkin' too much (help me)"},
        {"time": 20, "text": "I've been thinkin' too much (I've been thinkin' too much)"},
        {"time": 20, "text": "I've been thinkin' too much (help me)"}
      ]
    },
    {
      "id": 4,
      "title": "I'm Not The Only One",
      "lyrics": [
        {"time": 0, "text": "You and me we made a vow"},
        {"time": 5, "text": "For better or for worse"},
        {"time": 10, "text": "I can't believe you let me down"},
        {"time": 15, "text": "But the proof is in the way it hurts"},
        {"time": 15, "text": "For months on end, I've had my doubts"},
        {"time": 15, "text": "Denyin' every tear"},
        {"time": 15, "text": "I wish this would be over now"},
        {"time": 15, "text": "But I know that I still need you here"},
        {"time": 15, "text": "You say I'm crazy"},
        {"time": 15, "text": "'Cause you don't think I know what you've done"},
        {"time": 15, "text": "But when you call me \"baby\""},
        {"time": 15, "text": "I know I'm not the only one"},
        {"time": 15, "text": "You've been so unavailable"},
        {"time": 15, "text": "Now, sadly, I know why"},
        {"time": 15, "text": "Your heart is unobtainable"},
        {"time": 15, "text": "Even though Lord knows you kept mine"},
        {"time": 15, "text": "You say I'm crazy"},
        {"time": 15, "text": "'Cause you don't think I know what you've done"},
        {"time": 15, "text": "But when you call me \"baby\""},
        {"time": 15, "text": "I know I'm not the only one"},
        {"time": 15, "text": "I have loved you for many years"},
        {"time": 15, "text": "Maybe I am just not enough"},
        {"time": 15, "text": "You've made me realise my deepest fear"},
        {"time": 15, "text": "By lyin' and tearin' us up"},
        {"time": 15, "text": "You say I'm crazy"},
        {"time": 15, "text": "'Cause you don't think I know what you've done"},
        {"time": 15, "text": "But when you call me \"baby\""},
        {"time": 15, "text": "I know I'm not the only one"},
        {"time": 15, "text": "You say I'm crazy"},
        {"time": 15, "text": "'Cause you don't think I know what you've done"},
        {"time": 15, "text": "But when you call me \"baby\""},
        {"time": 15, "text": "I know I'm not the only one"},
        {"time": 15, "text": "I know I'm not the only one"},
        {"time": 15, "text": "I know I'm not the only one"},
        {"time": 15, "text": "And I know, and I know, and I know, and I know, and I know, and I know, know"},
        {"time": 15, "text": "I know I'm not the only one"}
      ]
    },
    {
      "id": 5,
      "title": "Red",
      "lyrics": [
        {"time": 0, "text": "Loving him is like..."},
        {"time": 5, "text": "Driving a new Maserati"},
        {"time": 10, "text": "Down a dead-end street"},
        {"time": 15, "text": "Faster than the wind"},
        {"time": 15, "text": "Passionate as sin, ended so suddenly"},
        {"time": 15, "text": "Loving him is like trying to change your mind"},
        {"time": 15, "text": "Once you're already flying through the free fall"},
        {"time": 15, "text": "Like the colors in autumn"},
        {"time": 15, "text": "So bright just before they lose it all"},
        {"time": 15, "text": "Losing him was blue like I'd never known"},
        {"time": 15, "text": "Missing him was dark grey all alone"},
        {"time": 15, "text": "Forgetting him was like trying to know somebody you've never met"},
        {"time": 15, "text": "Loving him was red"},
        {"time": 15, "text": "Loving him was red"},
        {"time": 15, "text": "Touching him is like realizing all you ever wanted was right there in front of you"},
        {"time": 15, "text": "Memorizing him was as easy as knowing all the words to your old favorite tune"},
        {"time": 15, "text": "Fighting with him was like trying to solve a crossword and realizing there's no right answer"},
        {"time": 15, "text": "Regretting him was like wishing you never found out that love could be that strong"},
        {"time": 15, "text": "Losing him was blue like I'd never known"},
        {"time": 15, "text": "Missing him was dark grey all alone"},
        {"time": 15, "text": "Forgetting him was like trying to know somebody you've never met"},
        {"time": 15, "text": "But loving him was red"},
        {"time": 15, "text": "Oh red burning red"},
        {"time": 15, "text": "Remembering him comes in flashbacks and echoes"},
        {"time": 15, "text": "Tell myself its time now, gotta let go"},
        {"time": 15, "text": "But moving on from him is impossible"},
        {"time": 15, "text": "When I still see it all in my head"},
        {"time": 15, "text": "Burning red."},
        {"time": 15, "text": "Burning, it was red."},
        {"time": 15, "text": "Oh, losing him was blue like I'd never known"},
        {"time": 15, "text": "Missing him was dark grey all alone"},
        {"time": 15, "text": "Forgetting him was like trying to know somebody you've never met"},
        {"time": 15, "text": "Cause loving him was red"},
        {"time": 15, "text": "Yeah, yeah red"},
        {"time": 15, "text": "We're burning red"},
        {"time": 15, "text": "And that's why he's spinning round in my head"},
        {"time": 15, "text": "Comes back to me burning red"},
        {"time": 15, "text": "Yeah yeah"},
        {"time": 15, "text": "His love was like driving a new Maserati down a dead end street."}
      ]
    }
  ]
}